claude_cli/__init__.py
claude_cli/claude.py
claude_cli/config.py
claude_cli/file.py
claude_cli/helpers.py
claude_cli/api/client.py
claude_cli/cli/__init__.py
claude_cli/cli/accounts.py
claude_cli/cli/chat.py
claude_cli/cli/conversations.py
claude_cli/cli/settings.py
unofficial_claude_cli-0.7.3.dist-info/licenses/LICENSE
unofficial_claude_cli-0.7.3.dist-info/METADATA
unofficial_claude_cli-0.7.3.dist-info/WHEEL
unofficial_claude_cli-0.7.3.dist-info/entry_points.txt
unofficial_claude_cli-0.7.3.dist-info/top_level.txt
unofficial_claude_cli-0.7.3.dist-info/RECORD
