Metadata-Version: 2.4
Name: unofficial-claude-cli
Version: 0.7.3
Summary: A CLI and API for interacting with Claude
Home-page: https://github.com/TheTank10/claude-cli
Author: TheTank10
License: MIT
Project-URL: Bug Reports, https://github.com/TheTank10/claude-cli/issues
Project-URL: Source, https://github.com/TheTank10/claude-cli
Keywords: claude ai cli api chatbot
Classifier: Development Status :: 4 - Beta
Classifier: Intended Audience :: Developers
Classifier: License :: OSI Approved :: MIT License
Classifier: Programming Language :: Python :: 3.10
Classifier: Programming Language :: Python :: 3.11
Classifier: Topic :: Software Development :: Libraries :: Python Modules
Classifier: Topic :: Communications :: Chat
Requires-Python: >=3.10
License-File: LICENSE
Requires-Dist: click>=8.0
Requires-Dist: requests>=2.28.0
Requires-Dist: rich>=13.0
Dynamic: author
Dynamic: classifier
Dynamic: description
Dynamic: description-content-type
Dynamic: home-page
Dynamic: keywords
Dynamic: license
Dynamic: license-file
Dynamic: project-url
Dynamic: requires-dist
Dynamic: requires-python
Dynamic: summary
